{
    "categories":[
        {
            "name": "Αποτελεσμα"
        },
        {
            "name": "Over/Under"
        },
        {
            "name": "Goal Goal"
        },
        {
            "name": "GG & Over/Under"
        },
        {
            "name": "Αποτελεσμα & Ο/U"
        },
        {
            "name": "Αποτελεσμα & GG"
        },
        {
            "name": "Συνολικα Γκολ"
        },
        {
            "name": "Ασιατικο"
        },
        {
            "name": "Διπλη Ευκαιρια"
        },
        {
            "name": "Διπλη Ευκαιρια & O/U"
        },
        {
            "name": "Διπλη Ευκαιρια & GG"
        },
        {
            "name": "Επομενο Γκολ"
        },
        {
            "name": "Συνολικα Κορνερ"
        },
        {
            "name": "Νικητης Κορνερ"
        },
        {
            "name": "Ακριβες Σκορ"
        },
        {
            "name": "Draw No Bet"
        },
        {
            "name": "Νικητης Ημιχρονο"
        },
        {
            "name": "Ημιχρονο/Τελικο"
        },
        {
            "name": "Ημιχρονο/Τελικο & O/U"
        },
        {
            "name": "Ημιχρονο/Τελικο & GG"
        },
        {
            "name": "Σκορερ"
        },
        {
            "name": "Καρτες"
        },
        {
            "name": "Bet Builder"
        }
    ]
}